tox4.py
tox4-0.0.0.dist-info/LICENSE
tox4-0.0.0.dist-info/WHEEL
tox4-0.0.0.dist-info/METADATA
tox4-0.0.0.dist-info/RECORD
