Metadata-Version: 2.1
Name: tox4
Version: 0.0.0
Summary: shim module for running 'pipx run tox4'
Author-email: Thomas Grainger <tox4@graingert.co.uk>
Classifier: License :: OSI Approved :: MIT License
Requires-Dist: tox>=4.0.0a10
Project-URL: Home, https://github.com/graingert/tox4
